mergegi/__init__.py
mergegi/cli.py
mergegi/mergegi.py
mergegi/samplesheet_converter.py
sequana_pipelines/mergegi/__init__.py
sequana_pipelines/mergegi/config.yml
sequana_pipelines/mergegi/main.py
sequana_pipelines/mergegi/mergegi.smk
mergegi-0.2.2.dist-info/WHEEL
mergegi-0.2.2.dist-info/entry_points.txt
mergegi-0.2.2.dist-info/LICENSE
mergegi-0.2.2.dist-info/METADATA
mergegi-0.2.2.dist-info/RECORD
