Metadata-Version: 2.1
Name: mergegi
Version: 0.2.2
Summary: Merge MGI fastq files
License: BSD-4-Clause
Keywords: fastq,MGI,merger
Author: Sequana Team
Requires-Python: >=3.8.1,<4.0.0
Classifier: License :: OSI Approved :: BSD License
Classifier: License :: Other/Proprietary License
Classifier: Operating System :: Unix
Classifier: Programming Language :: Python :: 3
Classifier: Programming Language :: Python :: 3.9
Classifier: Programming Language :: Python :: 3.10
Classifier: Programming Language :: Python :: 3.11
Classifier: Programming Language :: Python :: 3.10
Classifier: Programming Language :: Python :: 3.8
Classifier: Programming Language :: Python :: 3.9
Provides-Extra: sequana
Requires-Dist: click (>=8.1.3,<9.0.0)
Requires-Dist: sequana_pipetools (>=0.10.1,<0.11.0) ; extra == "sequana"
Requires-Dist: snakemake (>=7.19.1,<8.0.0) ; extra == "sequana"
Project-URL: Bug Tracker, https://github.com/sequana/MergeGI/issues
Project-URL: Homepage, https://github.com/sequana/MergeGI
